typed_prompt/__init__.py
typed_prompt/exceptions.py
typed_prompt/py.typed
typed_prompt/template.py
typed_prompt-0.1.4.dist-info/METADATA
typed_prompt-0.1.4.dist-info/WHEEL
typed_prompt-0.1.4.dist-info/licenses/LICENSE
typed_prompt-0.1.4.dist-info/RECORD
