Metadata-Version: 2.4
Name: typed-prompt
Version: 0.1.4
Summary: A simple type-safe, validated prompt management system for LLMs
Project-URL: Homepage, https://github.com/SamBroomy/typed-prompt
Project-URL: Documentation, https://github.com/SamBroomy/typed-prompt#readme
Project-URL: Repository, https://github.com/SamBroomy/typed-prompt.git
Project-URL: Changelog, https://github.com/SamBroomy/typed-prompt/blob/main/CHANGELOG.md
Author-email: SamBroomy <36888606+SamBroomy@users.noreply.github.com>
License-File: LICENSE
Keywords: jinja2,llm,prompt-engineering,pydantic,templating,type-safety
Classifier: Development Status :: 3 - Alpha
Classifier: Intended Audience :: Developers
Classifier: License :: OSI Approved :: MIT License
Classifier: Programming Language :: Python :: 3.10
Classifier: Programming Language :: Python :: 3.11
Classifier: Topic :: Software Development :: Libraries :: Python Modules
Classifier: Typing :: Typed
Requires-Python: >=3.10
Requires-Dist: jinja2>=3.0.1
Requires-Dist: pydantic>=2.0.0
